{
  "timestamp": "2025-08-29T15:26:05.808646+00:00",
  "market_open": true,
  "session_type": "MARKET",
  "positions": {
    "TSLA": {
      "symbol": "TSLA",
      "is_open": true,
      "entry_price": 322.2,
      "entry_time": "2025-08-20T14:15:18.654570",
      "last_signal": "HOLD",
      "last_confidence": 0.775086495009766,
      "realtime_pnl_pct": 5.25,
      "realtime_pnl_dollar": 1691.0,
      "current_price": 339.11
    },
    "HOOD": {
      "symbol": "HOOD",
      "is_open": false,
      "entry_price": 0.0,
      "entry_time": null,
      "last_signal": "HOLD",
      "last_confidence": 0.49007770258465416
    },
    "COIN": {
      "symbol": "COIN",
      "is_open": true,
      "entry_price": 305.7388,
      "entry_time": "2025-08-19T16:56:26.391163",
      "last_signal": "HOLD",
      "last_confidence": 0.6607298591394044,
      "realtime_pnl_pct": -0.58,
      "realtime_pnl_dollar": -178.38,
      "current_price": 303.955
    },
    "PLTR": {
      "symbol": "PLTR",
      "is_open": true,
      "entry_price": 163.845,
      "entry_time": "2025-08-19T16:13:09.801014",
      "last_signal": "HOLD",
      "last_confidence": 0.7497131790045409,
      "realtime_pnl_pct": -4.41,
      "realtime_pnl_dollar": -722.5,
      "current_price": 156.62
    },
    "AAPL": {
      "symbol": "AAPL",
      "is_open": true,
      "entry_price": 226.7,
      "entry_time": "2025-08-20T17:30:22.955922",
      "last_signal": "HOLD",
      "last_confidence": 0.5533601630959308,
      "realtime_pnl_pct": 2.7,
      "realtime_pnl_dollar": 613.0,
      "current_price": 232.83
    }
  },
  "latest_prices": {
    "TSLA": 345.56,
    "HOOD": 104.43,
    "COIN": 311.525,
    "PLTR": 156.945,
    "AAPL": 231.35
  },
  "realtime_prices": {
    "TSLA": 339.11,
    "HOOD": 103.59,
    "COIN": 303.955,
    "PLTR": 156.62,
    "AAPL": 232.83
  },
  "last_price_update": "2025-08-29T15:25:32.859881+00:00"
}